[{"authors":["admin"],"categories":null,"content":"Chengbin Pang is a PhD candidate of computer science and technology at Nanjing University. His researcch interests include system and software security.\nChengbin Pang是南京大学计算机科学与技术系的在读博士生。他的研究方向包括系统与软件安全。\n","date":-62135596800,"expirydate":-62135596800,"kind":"term","lang":"en","lastmod":-62135596800,"objectID":"2525497d367e79493fd32b198b28f040","permalink":"pangbin2415.github.io/author/chengbin-pang/","publishdate":"0001-01-01T00:00:00Z","relpermalink":"pangbin2415.github.io/author/chengbin-pang/","section":"authors","summary":"Chengbin Pang is a PhD candidate of computer science and technology at Nanjing University. His researcch interests include system and software security.\nChengbin Pang是南京大学计算机科学与技术系的在读博士生。他的研究方向包括系统与软件安全。","tags":null,"title":"Chengbin Pang","type":"authors"},{"authors":["Chengbin Pang","Hongbin Liu","Yifan Wang","Neil Zhenqiang Gong","Bing Mao","Jun Xu"],"categories":[],"content":"","date":1672531200,"expirydate":-62135596800,"kind":"page","lang":"en","lastmod":1683125453,"objectID":"160d2ff10c4d983489f73090f0256dfa","permalink":"pangbin2415.github.io/publication/pang-2023-generation/","publishdate":"2023-05-03T15:31:07.482947Z","relpermalink":"pangbin2415.github.io/publication/pang-2023-generation/","section":"publication","summary":"","tags":[],"title":"Generation-based fuzzing? Don’t build a new generator, reuse! (Computers \u0026 Security)","type":"publication"},{"authors":["Chengbin Pang","Tiantai Zhang","Linzhang Wang","Bing Mao"],"categories":[],"content":"","date":1672531200,"expirydate":-62135596800,"kind":"page","lang":"en","lastmod":1683127125,"objectID":"77613c027a2a5b09138023aa97dd0592","permalink":"pangbin2415.github.io/publication/pang-2023-issta/","publishdate":"2023-05-03T15:31:07.176421Z","relpermalink":"pangbin2415.github.io/publication/pang-2023-issta/","section":"publication","summary":"","tags":[],"title":"OCFI: Make Function Entry Identification Hard Again (ISSTA 2023)","type":"publication"},{"authors":["Yuchen Zhang","Chengbin Pang","Georgios Portokalidis","Nikos Triandopoulos","Jun Xu"],"categories":[],"content":"","date":1640995200,"expirydate":-62135596800,"kind":"page","lang":"en","lastmod":1683125453,"objectID":"2a13d157c19072f9695ace3d382fd4f5","permalink":"pangbin2415.github.io/publication/zhang-2022-debloating/","publishdate":"2023-05-03T15:31:07.709776Z","relpermalink":"pangbin2415.github.io/publication/zhang-2022-debloating/","section":"publication","summary":"","tags":[],"title":"Debloating Address Sanitizer (Usenix Security 2022)","type":"publication"},{"authors":["Chengbin Pang","Tiantai Zhang","Ruotong Yu","Bing Mao","Jun Xu"],"categories":[],"content":"","date":1640995200,"expirydate":-62135596800,"kind":"page","lang":"en","lastmod":1683125453,"objectID":"52797d9d96de44a1193eb7424148898e","permalink":"pangbin2415.github.io/publication/pang-2022-ground/","publishdate":"2023-05-03T15:31:07.598571Z","relpermalink":"pangbin2415.github.io/publication/pang-2022-ground/","section":"publication","summary":"","tags":[],"title":"Ground Truth for Binary Disassembly is Not Easy (Usenix Security 2022)","type":"publication"},{"authors":["Chengbin Pang","Ruotong Yu","Yaohui Chen","Eric Koskinen","Georgios Portokalidis","Bing Mao","Jun Xu"],"categories":null,"content":"","date":1609459200,"expirydate":-62135596800,"kind":"page","lang":"en","lastmod":1609459200,"objectID":"207678203572e1c171ab461bd73a69e6","permalink":"pangbin2415.github.io/publication/sok-sp-20/","publishdate":"2023-05-03T15:31:07.951592Z","relpermalink":"pangbin2415.github.io/publication/sok-sp-20/","section":"publication","summary":"","tags":null,"title":"SoK: All You Ever Wanted to Know About x86/x64 Binary Disassembly But Were Afraid to Ask (SP 2021)","type":"publication"},{"authors":["Chengbin Pang","Ruotong Yu","Dongpeng Xu","Eric Koskinen","Georgios Portokalidis","Jun Xu"],"categories":[],"content":"","date":1609459200,"expirydate":-62135596800,"kind":"page","lang":"en","lastmod":1624722202,"objectID":"a681831f1f0cab87a958caf74fe16086","permalink":"pangbin2415.github.io/publication/pang-2021-towards/","publishdate":"2023-05-03T15:31:07.826709Z","relpermalink":"pangbin2415.github.io/publication/pang-2021-towards/","section":"publication","summary":"","tags":[],"title":"Towards Optimal Use of Exception Handling Information for Function Detection (DSN 2021)","type":"publication"},{"authors":["Chengbin Pang","Jun Xu","Eric Koskinen"],"categories":[],"content":"","date":1577836800,"expirydate":-62135596800,"kind":"page","lang":"en","lastmod":1601293851,"objectID":"b47a915a70b1e0f5c76284224a5179be","permalink":"pangbin2415.github.io/publication/blackhat-2020/","publishdate":"2023-05-03T15:31:08.062993Z","relpermalink":"pangbin2415.github.io/publication/blackhat-2020/","section":"publication","summary":"","tags":[],"title":"Demystify Today's Binary Disassembling and How Modern ABI Makes it Easier (BlackHat Asia 2020)","type":"publication"},{"authors":["Chengbin Pang","Yunlan Du","Bing Mao","Shanqing Guo"],"categories":null,"content":"","date":1514764800,"expirydate":-62135596800,"kind":"page","lang":"en","lastmod":1514764800,"objectID":"4ebaa3115aea332d22924a76e83534bb","permalink":"pangbin2415.github.io/publication/pang-2018-mapping/","publishdate":"2023-05-03T15:31:08.179904Z","relpermalink":"pangbin2415.github.io/publication/pang-2018-mapping/","section":"publication","summary":"","tags":null,"title":"Mapping to bits: Efficiently detecting type confusion errors (ACSAC 2018)","type":"publication"},{"authors":["Zhilong Wang","Xuhua Ding","Chengbin Pang","Jian Guo","Jun Zhu","Bing Mao"],"categories":null,"content":"","date":1514764800,"expirydate":-62135596800,"kind":"page","lang":"en","lastmod":1514764800,"objectID":"951378d4f2fbfb21a43e9872a616768d","permalink":"pangbin2415.github.io/publication/wang-2018-detect/","publishdate":"2023-05-03T15:31:08.293373Z","relpermalink":"pangbin2415.github.io/publication/wang-2018-detect/","section":"publication","summary":"","tags":null,"title":"To detect stack buffer overflow with polymorphic canaries (DSN 2018)","type":"publication"}]